LICENSE
MANIFEST.in
README.md
setup.py
imgmaker/__init__.py
imgmaker/cli.py
imgmaker/imgmaker.py
imgmaker.egg-info/PKG-INFO
imgmaker.egg-info/SOURCES.txt
imgmaker.egg-info/dependency_links.txt
imgmaker.egg-info/entry_points.txt
imgmaker.egg-info/requires.txt
imgmaker.egg-info/top_level.txt
imgmaker/templates/github-social/config.yaml
imgmaker/templates/github-social/github-social.html
imgmaker/templates/hero/config.yaml
imgmaker/templates/hero/hero.html
imgmaker/templates/meme/config.yaml
imgmaker/templates/meme/meme.html
imgmaker/templates/watermark/config.yaml
imgmaker/templates/watermark/watermark.html