Metadata-Version: 2.1
Name: imgmaker
Version: 0.4
Summary: Create high-quality images programmatically using easily-hackable templates.
Home-page: https://github.com/minimaxir/imgmaker
Author: Max Woolf
Author-email: max@minimaxir.com
License: MIT
Keywords: images,image generation,cool stuff
Requires-Python: >=3.6
License-File: LICENSE
Requires-Dist: selenium
Requires-Dist: jinja2
Requires-Dist: Pillow
Requires-Dist: requests
Requires-Dist: fire>=0.3.0
Requires-Dist: markdown
Requires-Dist: psutil
Requires-Dist: pyyaml
Requires-Dist: pngquant
